<?xml version="1.0" encoding="utf-8"?>
<resources xmlns:tools="http://schemas.android.com/tools" tools:ignore="MissingTranslation">
    <bool name="next_gtfs_rts_schedule_available">true</bool>
    <bool name="next_gtfs_rts_frequency_available">false</bool>
    <string name="next_gtfs_rts_area_min_lat">43.592119</string>
    <string name="next_gtfs_rts_area_max_lat">43.909529</string>
    <string name="next_gtfs_rts_area_min_lng">-79.649904</string>
    <string name="next_gtfs_rts_area_max_lng">-79.123046</string>
    <integer name="next_gtfs_rts_first_departure_in_sec">1557646860</integer>
    <integer name="next_gtfs_rts_last_departure_in_sec">1561285490</integer>
</resources>
